{
    "images":
    {
	
		"black":
        {
            "image" : "custommainmenu:textures/gui/bg_menu.png",
            "posX" : 29,
            "posY" : 0,
            "width" : 155,
            "height" : 800,
            "alignment" : "top_left"
        }
	
	},
    
    "buttons":
    {     
		"singleplayer":
        {
            "text" : "Singleplayer",
			"normalTextColor" : 12303291,
			"hoverTextColor" : 3125670,
			"texture" : "custommainmenu:textures/gui/btn.png",
            "posX" : 30,
            "posY" : -70,
            "width" : 153,
            "height" : 20,
			imageWidth : 100,
			imageHeight : 50,
			"alignment" : "left_center",
            "action" : 
            {
                "type" : "openGui",
                "gui" : "singleplayer"
            }
        },		

		"multiplayer":
        {
            "text" : "Rejoindre le serveur",			
			"normalTextColor" : 13938487,
			"hoverTextColor" : 14938487,
			"texture" : "custommainmenu:textures/gui/btn.png",
            "posX" : 30,
            "posY" : -50,
            "width" : 153,
            "height" : 20,
			imageWidth : 100,
			imageHeight : 50,
			"alignment" : "left_center",
            "action" : 
            {
                "type" : "connectToServer",
                "ip" : "play.pixelmonlegends.com"
            }
        },
               
		"options":
        {
            "text" : "Options",
			"normalTextColor" : 12303291,
			"hoverTextColor" : 3125670,
			"texture" : "custommainmenu:textures/gui/btn.png",
            "posX" : 30,
            "posY" : -10,
            "width" : 153,
            "height" : 20,
			imageWidth : 100,
			imageHeight : 50,
			"alignment" : "left_center",
            "action" : 
            {
                "type" : "openGui",
                "gui" : "options"
            }
        },
		        
		"language":
        {
            "text" : "Language",
			"normalTextColor" : 12303291,
			"hoverTextColor" : 3125670,
			"texture" : "custommainmenu:textures/gui/btn.png",
            "posX" : 30,
            "posY" : 10,
            "width" : 153,
            "height" : 20,
			imageWidth : 100,
			imageHeight : 50,			
			"alignment" : "left_center",
            "action" : 
            {
                "type" : "openGui",
                "gui" : "languages"
            }
        },
                    
        "quit":
        {
            "text" : "Quitter",
			"normalTextColor" : 16729156,
			"hoverTextColor" : 14483456,
			"texture" : "custommainmenu:textures/gui/btn.png",
            "posX" : 30,
            "posY" : 30,
            "width" : 153,
            "height" : 20,
			imageWidth : 100,
			imageHeight : 50,
			"alignment" : "left_center",
			"hoverText" : "A la prochaine!",
            "action" : 
            {
                "type" : "quit"
            }
        },
		
        "mods":
        {
            "text" : "Mods (#modsloaded#/#modsactive#)",
			"normalTextColor" : 12303291,
			"hoverTextColor" : 3125670,
			"texture" : "custommainmenu:textures/gui/btn.png",
            "posX" : 30,
            "posY" : 80,
            "width" : 153,
            "height" : 20,
			imageWidth : 100,
			imageHeight : 50,
			imageWidth : 100,
			imageHeight : 50,
			"alignment" : "left_center",
            "action" : 
            {
                "type" : "openGui",
                "gui" : "mods"
            }
        }
	},
    
	
	"alignments":
    {
        "c1":
        {
            "factorWidth" : 0.5,
            "factorHeight" : 0.7
        },
 
        "c2":
        {
            "factorWidth" : 0.2,
            "factorHeight" : 0.2
        }
    },
	
    "other":
    {
		"background":
		{
			"image" : "custommainmenu:textures/gui/background.jpg",
			"mode" : "stretch"
		}
    }
}